escam_toolbox/__init__.py
escam_toolbox/dicom.py
escam_toolbox/example_app1.py
escam_toolbox/example_app2.py
escam_toolbox/process.py
escam_toolbox/timing.py
escam_toolbox/ui.py
escam_toolbox-1.0.9.dist-info/AUTHORS.rst
escam_toolbox-1.0.9.dist-info/LICENSE
escam_toolbox-1.0.9.dist-info/METADATA
escam_toolbox-1.0.9.dist-info/WHEEL
escam_toolbox-1.0.9.dist-info/entry_points.txt
escam_toolbox-1.0.9.dist-info/top_level.txt
escam_toolbox-1.0.9.dist-info/RECORD
