Metadata-Version: 2.1
Name: escam-toolbox
Version: 1.0.9
Summary: Toolkit with radiomics utilities and UI compponents
Home-page: https://github.com/rbrecheisen/escam_toolbox
Author: Ralph Brecheisen
Author-email: r.brecheisen@maastrichtuniversity.nl
License: MIT license
Keywords: escam_toolbox
Platform: UNKNOWN
Classifier: Development Status :: 2 - Pre-Alpha
Classifier: Intended Audience :: Developers
Classifier: License :: OSI Approved :: MIT License
Classifier: Natural Language :: English
Classifier: Programming Language :: Python :: 2
Classifier: Programming Language :: Python :: 2.7
Classifier: Programming Language :: Python :: 3
Classifier: Programming Language :: Python :: 3.4
Classifier: Programming Language :: Python :: 3.5
Classifier: Programming Language :: Python :: 3.6
Classifier: Programming Language :: Python :: 3.7
Requires-Dist: pyradiomics
Requires-Dist: pandas
Requires-Dist: pydicom
Requires-Dist: SimpleITK
Requires-Dist: pillow
